flask_anticsrf.py
Flask_AntiCsrf-0.0.2.dist-info/LICENSE
Flask_AntiCsrf-0.0.2.dist-info/METADATA
Flask_AntiCsrf-0.0.2.dist-info/WHEEL
Flask_AntiCsrf-0.0.2.dist-info/top_level.txt
Flask_AntiCsrf-0.0.2.dist-info/RECORD
