Metadata-Version: 2.1
Name: Flask-AntiCsrf
Version: 0.0.2
Summary: Experimental anti-CSRF library for Flask apps
Home-page: https://github.com/skylerberg/Flask-AntiCsrf
Author: Skyler Berg
Author-email: skylertheberg@gmail.com
License: UNKNOWN
Keywords: csrf xsrf security flask
Platform: UNKNOWN
Classifier: Development Status :: 3 - Alpha
Classifier: Environment :: Web Environment
Classifier: License :: OSI Approved :: Apache Software License
Classifier: Operating System :: OS Independent
Classifier: Programming Language :: Python
Classifier: Programming Language :: Python :: 2
Classifier: Programming Language :: Python :: 2.7
Classifier: Programming Language :: Python :: 3
Classifier: Programming Language :: Python :: 3.5
Classifier: Programming Language :: Python :: 3.6
Classifier: Programming Language :: Python :: 3.7
Classifier: Topic :: Internet :: WWW/HTTP
Classifier: Topic :: Security
Classifier: Topic :: Software Development :: Libraries :: Python Modules
Requires-Dist: Flask
